{"flowContents":{"identifier":"815cd357-11aa-3cfb-aaac-b1dd73c18e5d","instanceIdentifier":"d5eb44f8-0193-1000-0000-00003ed74031","name":"GovCloud CDP SE Start/Stop","comments":"","position":{"x":304.0,"y":440.0},"processGroups":[],"remoteProcessGroups":[],"processors":[{"identifier":"9b982326-c6fa-31ff-81f4-5a4c320d1423","instanceIdentifier":"f1de315f-6cd4-1df8-b924-d164223f401b","name":"ExecuteStreamCommand","comments":"","position":{"x":-72.0,"y":968.0},"type":"org.apache.nifi.processors.standard.ExecuteStreamCommand","bundle":{"group":"org.apache.nifi","artifact":"nifi-standard-nar","version":"1.26.0.2.1.7.1000-46"},"properties":{"argumentsStrategy":"Dynamic Property Arguments","Max Attribute Length":"256","Output MIME Type":null,"Working Directory":"/var/lib/nifi/scripts/CDP_Suspend_Resources","Command Path":"/bin/bash","Output Destination Attribute":null,"Argument Delimiter":";","Ignore STDIN":"false","command.argument.0":"start-environments.sh","Command Arguments":"stop-datahubs.sh cdp-se-gov-demo-dd,cdp-se-demo-dh,cdp-se-gov-dm-dh","command.argument.1":"cdp-se-gov-demo-env"},"propertyDescriptors":{"argumentsStrategy":{"name":"argumentsStrategy","displayName":"Command Arguments Strategy","identifiesControllerService":false,"sensitive":false},"Max Attribute Length":{"name":"Max Attribute Length","displayName":"Max Attribute Length","identifiesControllerService":false,"sensitive":false},"Output MIME Type":{"name":"Output MIME Type","displayName":"Output MIME Type","identifiesControllerService":false,"sensitive":false},"Working Directory":{"name":"Working Directory","displayName":"Working Directory","identifiesControllerService":false,"sensitive":false},"Command Path":{"name":"Command Path","displayName":"Command Path","identifiesControllerService":false,"sensitive":false},"Output Destination Attribute":{"name":"Output Destination Attribute","displayName":"Output Destination Attribute","identifiesControllerService":false,"sensitive":false},"Argument Delimiter":{"name":"Argument Delimiter","displayName":"Argument Delimiter","identifiesControllerService":false,"sensitive":false},"Ignore STDIN":{"name":"Ignore STDIN","displayName":"Ignore STDIN","identifiesControllerService":false,"sensitive":false},"command.argument.0":{"name":"command.argument.0","displayName":"command.argument.0","identifiesControllerService":false,"sensitive":false},"Command Arguments":{"name":"Command Arguments","displayName":"Command Arguments","identifiesControllerService":false,"sensitive":false},"command.argument.1":{"name":"command.argument.1","displayName":"command.argument.1","identifiesControllerService":false,"sensitive":false}},"style":{},"schedulingPeriod":"0 sec","schedulingStrategy":"TIMER_DRIVEN","executionNode":"ALL","penaltyDuration":"30 sec","yieldDuration":"1 sec","bulletinLevel":"WARN","runDurationMillis":0,"concurrentlySchedulableTaskCount":1,"autoTerminatedRelationships":["output stream","original","nonzero status"],"scheduledState":"ENABLED","retryCount":1,"retriedRelationships":["nonzero status"],"backoffMechanism":"PENALIZE_FLOWFILE","maxBackoffPeriod":"10 mins","componentType":"PROCESSOR","groupIdentifier":"815cd357-11aa-3cfb-aaac-b1dd73c18e5d"},{"identifier":"9e1fc974-7d07-3f2f-aeec-fbade8950c0f","instanceIdentifier":"a3e131fd-121a-14ab-b802-c5ac06e5cc30","name":"GenerateFlowFile","comments":"","position":{"x":544.0,"y":728.0},"type":"org.apache.nifi.processors.standard.GenerateFlowFile","bundle":{"group":"org.apache.nifi","artifact":"nifi-standard-nar","version":"1.26.0.2.1.7.1000-46"},"properties":{"character-set":"UTF-8","File Size":"0B","mime-type":null,"generate-ff-custom-text":null,"Batch Size":"1","Unique FlowFiles":"false","Data Format":"Text"},"propertyDescriptors":{"character-set":{"name":"character-set","displayName":"Character Set","identifiesControllerService":false,"sensitive":false},"File Size":{"name":"File Size","displayName":"File Size","identifiesControllerService":false,"sensitive":false},"mime-type":{"name":"mime-type","displayName":"Mime Type","identifiesControllerService":false,"sensitive":false},"generate-ff-custom-text":{"name":"generate-ff-custom-text","displayName":"Custom Text","identifiesControllerService":false,"sensitive":false},"Batch Size":{"name":"Batch Size","displayName":"Batch Size","identifiesControllerService":false,"sensitive":false},"Unique FlowFiles":{"name":"Unique FlowFiles","displayName":"Unique FlowFiles","identifiesControllerService":false,"sensitive":false},"Data Format":{"name":"Data Format","displayName":"Data Format","identifiesControllerService":false,"sensitive":false}},"style":{},"schedulingPeriod":"0 0 23 ? * MON-FRI *","schedulingStrategy":"CRON_DRIVEN","executionNode":"ALL","penaltyDuration":"30 sec","yieldDuration":"1 sec","bulletinLevel":"WARN","runDurationMillis":0,"concurrentlySchedulableTaskCount":1,"autoTerminatedRelationships":[],"scheduledState":"ENABLED","retryCount":10,"retriedRelationships":[],"backoffMechanism":"PENALIZE_FLOWFILE","maxBackoffPeriod":"10 mins","componentType":"PROCESSOR","groupIdentifier":"815cd357-11aa-3cfb-aaac-b1dd73c18e5d"},{"identifier":"bcc9cf26-45f5-31b6-8581-483021563543","instanceIdentifier":"340d3f11-9acf-1275-a253-e3e74d6722e8","name":"GenerateFlowFile","comments":"","position":{"x":-72.0,"y":728.0},"type":"org.apache.nifi.processors.standard.GenerateFlowFile","bundle":{"group":"org.apache.nifi","artifact":"nifi-standard-nar","version":"1.26.0.2.1.7.1000-46"},"properties":{"character-set":"UTF-8","File Size":"0B","mime-type":null,"generate-ff-custom-text":null,"Batch Size":"1","Unique FlowFiles":"false","Data Format":"Text"},"propertyDescriptors":{"character-set":{"name":"character-set","displayName":"Character Set","identifiesControllerService":false,"sensitive":false},"File Size":{"name":"File Size","displayName":"File Size","identifiesControllerService":false,"sensitive":false},"mime-type":{"name":"mime-type","displayName":"Mime Type","identifiesControllerService":false,"sensitive":false},"generate-ff-custom-text":{"name":"generate-ff-custom-text","displayName":"Custom Text","identifiesControllerService":false,"sensitive":false},"Batch Size":{"name":"Batch Size","displayName":"Batch Size","identifiesControllerService":false,"sensitive":false},"Unique FlowFiles":{"name":"Unique FlowFiles","displayName":"Unique FlowFiles","identifiesControllerService":false,"sensitive":false},"Data Format":{"name":"Data Format","displayName":"Data Format","identifiesControllerService":false,"sensitive":false}},"style":{},"schedulingPeriod":"0 0 12 ? * MON-FRI *","schedulingStrategy":"CRON_DRIVEN","executionNode":"ALL","penaltyDuration":"30 sec","yieldDuration":"1 sec","bulletinLevel":"WARN","runDurationMillis":0,"concurrentlySchedulableTaskCount":1,"autoTerminatedRelationships":[],"scheduledState":"ENABLED","retryCount":10,"retriedRelationships":[],"backoffMechanism":"PENALIZE_FLOWFILE","maxBackoffPeriod":"10 mins","componentType":"PROCESSOR","groupIdentifier":"815cd357-11aa-3cfb-aaac-b1dd73c18e5d"},{"identifier":"ff4b6344-1914-3983-b83b-638ecf3f6a5b","instanceIdentifier":"04813103-e9ec-1096-a010-ff5d5f10a3e5","name":"ExecuteStreamCommand","comments":"","position":{"x":-72.0,"y":480.0},"type":"org.apache.nifi.processors.standard.ExecuteStreamCommand","bundle":{"group":"org.apache.nifi","artifact":"nifi-standard-nar","version":"1.26.0.2.1.7.1000-46"},"properties":{"argumentsStrategy":"Dynamic Property Arguments","Max Attribute Length":"256","Output MIME Type":null,"Working Directory":"/var/lib/nifi/scripts/CDP_Suspend_Resources","Command Path":"/bin/bash","Output Destination Attribute":null,"Argument Delimiter":";","Ignore STDIN":"false","command.argument.0":"start-datahubs.sh","Command Arguments":"stop-datahubs.sh cdp-se-gov-demo-dd,cdp-se-demo-dh,cdp-se-gov-dm-dh","command.argument.1":"cdp-se-gov-demo-dd,cdp-se-de-dh,cdp-se-gov-dm-dh"},"propertyDescriptors":{"argumentsStrategy":{"name":"argumentsStrategy","displayName":"Command Arguments Strategy","identifiesControllerService":false,"sensitive":false},"Max Attribute Length":{"name":"Max Attribute Length","displayName":"Max Attribute Length","identifiesControllerService":false,"sensitive":false},"Output MIME Type":{"name":"Output MIME Type","displayName":"Output MIME Type","identifiesControllerService":false,"sensitive":false},"Working Directory":{"name":"Working Directory","displayName":"Working Directory","identifiesControllerService":false,"sensitive":false},"Command Path":{"name":"Command Path","displayName":"Command Path","identifiesControllerService":false,"sensitive":false},"Output Destination Attribute":{"name":"Output Destination Attribute","displayName":"Output Destination Attribute","identifiesControllerService":false,"sensitive":false},"Argument Delimiter":{"name":"Argument Delimiter","displayName":"Argument Delimiter","identifiesControllerService":false,"sensitive":false},"Ignore STDIN":{"name":"Ignore STDIN","displayName":"Ignore STDIN","identifiesControllerService":false,"sensitive":false},"command.argument.0":{"name":"command.argument.0","displayName":"command.argument.0","identifiesControllerService":false,"sensitive":false},"Command Arguments":{"name":"Command Arguments","displayName":"Command Arguments","identifiesControllerService":false,"sensitive":false},"command.argument.1":{"name":"command.argument.1","displayName":"command.argument.1","identifiesControllerService":false,"sensitive":false}},"style":{},"schedulingPeriod":"0 sec","schedulingStrategy":"TIMER_DRIVEN","executionNode":"ALL","penaltyDuration":"30 sec","yieldDuration":"1 sec","bulletinLevel":"WARN","runDurationMillis":0,"concurrentlySchedulableTaskCount":1,"autoTerminatedRelationships":["output stream","original","nonzero status"],"scheduledState":"ENABLED","retryCount":1,"retriedRelationships":["nonzero status"],"backoffMechanism":"PENALIZE_FLOWFILE","maxBackoffPeriod":"10 mins","componentType":"PROCESSOR","groupIdentifier":"815cd357-11aa-3cfb-aaac-b1dd73c18e5d"},{"identifier":"ade1b1fa-735c-3bcd-9e2c-bcd669a08fd5","instanceIdentifier":"f4c935a4-b333-179a-b062-b2750579df49","name":"GenerateFlowFile","comments":"","position":{"x":-72.0,"y":224.0},"type":"org.apache.nifi.processors.standard.GenerateFlowFile","bundle":{"group":"org.apache.nifi","artifact":"nifi-standard-nar","version":"1.26.0.2.1.7.1000-46"},"properties":{"character-set":"UTF-8","File Size":"0B","mime-type":null,"generate-ff-custom-text":null,"Batch Size":"1","Unique FlowFiles":"false","Data Format":"Text"},"propertyDescriptors":{"character-set":{"name":"character-set","displayName":"Character Set","identifiesControllerService":false,"sensitive":false},"File Size":{"name":"File Size","displayName":"File Size","identifiesControllerService":false,"sensitive":false},"mime-type":{"name":"mime-type","displayName":"Mime Type","identifiesControllerService":false,"sensitive":false},"generate-ff-custom-text":{"name":"generate-ff-custom-text","displayName":"Custom Text","identifiesControllerService":false,"sensitive":false},"Batch Size":{"name":"Batch Size","displayName":"Batch Size","identifiesControllerService":false,"sensitive":false},"Unique FlowFiles":{"name":"Unique FlowFiles","displayName":"Unique FlowFiles","identifiesControllerService":false,"sensitive":false},"Data Format":{"name":"Data Format","displayName":"Data Format","identifiesControllerService":false,"sensitive":false}},"style":{},"schedulingPeriod":"0 0 13 ? * MON-FRI *","schedulingStrategy":"CRON_DRIVEN","executionNode":"ALL","penaltyDuration":"30 sec","yieldDuration":"1 sec","bulletinLevel":"WARN","runDurationMillis":0,"concurrentlySchedulableTaskCount":1,"autoTerminatedRelationships":[],"scheduledState":"ENABLED","retryCount":10,"retriedRelationships":[],"backoffMechanism":"PENALIZE_FLOWFILE","maxBackoffPeriod":"10 mins","componentType":"PROCESSOR","groupIdentifier":"815cd357-11aa-3cfb-aaac-b1dd73c18e5d"},{"identifier":"81eb242a-10b5-3b5c-a035-01e2546e00db","instanceIdentifier":"d5ebeb21-0193-1000-ffff-ffffc2e64bfc","name":"GenerateFlowFile","comments":"","position":{"x":536.0,"y":216.0},"type":"org.apache.nifi.processors.standard.GenerateFlowFile","bundle":{"group":"org.apache.nifi","artifact":"nifi-standard-nar","version":"1.26.0.2.1.7.1000-46"},"properties":{"character-set":"UTF-8","File Size":"0B","mime-type":null,"generate-ff-custom-text":null,"Batch Size":"1","Unique FlowFiles":"false","Data Format":"Text"},"propertyDescriptors":{"character-set":{"name":"character-set","displayName":"Character Set","identifiesControllerService":false,"sensitive":false},"File Size":{"name":"File Size","displayName":"File Size","identifiesControllerService":false,"sensitive":false},"mime-type":{"name":"mime-type","displayName":"Mime Type","identifiesControllerService":false,"sensitive":false},"generate-ff-custom-text":{"name":"generate-ff-custom-text","displayName":"Custom Text","identifiesControllerService":false,"sensitive":false},"Batch Size":{"name":"Batch Size","displayName":"Batch Size","identifiesControllerService":false,"sensitive":false},"Unique FlowFiles":{"name":"Unique FlowFiles","displayName":"Unique FlowFiles","identifiesControllerService":false,"sensitive":false},"Data Format":{"name":"Data Format","displayName":"Data Format","identifiesControllerService":false,"sensitive":false}},"style":{},"schedulingPeriod":"0 0 0 ? * MON-FRI *","schedulingStrategy":"CRON_DRIVEN","executionNode":"ALL","penaltyDuration":"30 sec","yieldDuration":"1 sec","bulletinLevel":"WARN","runDurationMillis":0,"concurrentlySchedulableTaskCount":1,"autoTerminatedRelationships":[],"scheduledState":"ENABLED","retryCount":10,"retriedRelationships":[],"backoffMechanism":"PENALIZE_FLOWFILE","maxBackoffPeriod":"10 mins","componentType":"PROCESSOR","groupIdentifier":"815cd357-11aa-3cfb-aaac-b1dd73c18e5d"},{"identifier":"2c32f191-13a2-36d0-817a-8f9b40bd4329","instanceIdentifier":"d5ec1213-0193-1000-ffff-ffffcaf5eef1","name":"ExecuteStreamCommand","comments":"","position":{"x":536.0,"y":472.0},"type":"org.apache.nifi.processors.standard.ExecuteStreamCommand","bundle":{"group":"org.apache.nifi","artifact":"nifi-standard-nar","version":"1.26.0.2.1.7.1000-46"},"properties":{"argumentsStrategy":"Dynamic Property Arguments","Max Attribute Length":"256","Output MIME Type":null,"Working Directory":"/var/lib/nifi/scripts/CDP_Suspend_Resources","Command Path":"/bin/bash","Output Destination Attribute":null,"Argument Delimiter":";","Ignore STDIN":"false","command.argument.0":"stop-datahubs.sh","Command Arguments":"stop-datahubs.sh cdp-se-gov-demo-dd,cdp-se-demo-dh,cdp-se-gov-dm-dh","command.argument.1":"cdp-se-gov-demo-dd,cdp-se-de-dh,cdp-se-gov-dm-dh"},"propertyDescriptors":{"argumentsStrategy":{"name":"argumentsStrategy","displayName":"Command Arguments Strategy","identifiesControllerService":false,"sensitive":false},"Max Attribute Length":{"name":"Max Attribute Length","displayName":"Max Attribute Length","identifiesControllerService":false,"sensitive":false},"Output MIME Type":{"name":"Output MIME Type","displayName":"Output MIME Type","identifiesControllerService":false,"sensitive":false},"Working Directory":{"name":"Working Directory","displayName":"Working Directory","identifiesControllerService":false,"sensitive":false},"Command Path":{"name":"Command Path","displayName":"Command Path","identifiesControllerService":false,"sensitive":false},"Output Destination Attribute":{"name":"Output Destination Attribute","displayName":"Output Destination Attribute","identifiesControllerService":false,"sensitive":false},"Argument Delimiter":{"name":"Argument Delimiter","displayName":"Argument Delimiter","identifiesControllerService":false,"sensitive":false},"Ignore STDIN":{"name":"Ignore STDIN","displayName":"Ignore STDIN","identifiesControllerService":false,"sensitive":false},"command.argument.0":{"name":"command.argument.0","displayName":"command.argument.0","identifiesControllerService":false,"sensitive":false},"Command Arguments":{"name":"Command Arguments","displayName":"Command Arguments","identifiesControllerService":false,"sensitive":false},"command.argument.1":{"name":"command.argument.1","displayName":"command.argument.1","identifiesControllerService":false,"sensitive":false}},"style":{},"schedulingPeriod":"0 sec","schedulingStrategy":"TIMER_DRIVEN","executionNode":"ALL","penaltyDuration":"30 sec","yieldDuration":"1 sec","bulletinLevel":"WARN","runDurationMillis":0,"concurrentlySchedulableTaskCount":1,"autoTerminatedRelationships":["output stream","original","nonzero status"],"scheduledState":"ENABLED","retryCount":1,"retriedRelationships":["nonzero status"],"backoffMechanism":"PENALIZE_FLOWFILE","maxBackoffPeriod":"10 mins","componentType":"PROCESSOR","groupIdentifier":"815cd357-11aa-3cfb-aaac-b1dd73c18e5d"},{"identifier":"2b68ebe8-b050-3af5-a68d-c01b6ca83efa","instanceIdentifier":"1d8d3f74-ac39-15ac-90db-503ca4a7a46f","name":"ExecuteStreamCommand","comments":"","position":{"x":544.0,"y":968.0},"type":"org.apache.nifi.processors.standard.ExecuteStreamCommand","bundle":{"group":"org.apache.nifi","artifact":"nifi-standard-nar","version":"1.26.0.2.1.7.1000-46"},"properties":{"argumentsStrategy":"Dynamic Property Arguments","Max Attribute Length":"256","Output MIME Type":null,"Working Directory":"/var/lib/nifi/scripts/CDP_Suspend_Resources","Command Path":"/bin/bash","Output Destination Attribute":null,"Argument Delimiter":";","Ignore STDIN":"false","command.argument.0":"stop-environments.sh","Command Arguments":"stop-datahubs.sh cdp-se-gov-demo-dd,cdp-se-demo-dh,cdp-se-gov-dm-dh","command.argument.1":"cdp-se-gov-demo-env"},"propertyDescriptors":{"argumentsStrategy":{"name":"argumentsStrategy","displayName":"Command Arguments Strategy","identifiesControllerService":false,"sensitive":false},"Max Attribute Length":{"name":"Max Attribute Length","displayName":"Max Attribute Length","identifiesControllerService":false,"sensitive":false},"Output MIME Type":{"name":"Output MIME Type","displayName":"Output MIME Type","identifiesControllerService":false,"sensitive":false},"Working Directory":{"name":"Working Directory","displayName":"Working Directory","identifiesControllerService":false,"sensitive":false},"Command Path":{"name":"Command Path","displayName":"Command Path","identifiesControllerService":false,"sensitive":false},"Output Destination Attribute":{"name":"Output Destination Attribute","displayName":"Output Destination Attribute","identifiesControllerService":false,"sensitive":false},"Argument Delimiter":{"name":"Argument Delimiter","displayName":"Argument Delimiter","identifiesControllerService":false,"sensitive":false},"Ignore STDIN":{"name":"Ignore STDIN","displayName":"Ignore STDIN","identifiesControllerService":false,"sensitive":false},"command.argument.0":{"name":"command.argument.0","displayName":"command.argument.0","identifiesControllerService":false,"sensitive":false},"Command Arguments":{"name":"Command Arguments","displayName":"Command Arguments","identifiesControllerService":false,"sensitive":false},"command.argument.1":{"name":"command.argument.1","displayName":"command.argument.1","identifiesControllerService":false,"sensitive":false}},"style":{},"schedulingPeriod":"0 sec","schedulingStrategy":"TIMER_DRIVEN","executionNode":"ALL","penaltyDuration":"30 sec","yieldDuration":"1 sec","bulletinLevel":"WARN","runDurationMillis":0,"concurrentlySchedulableTaskCount":1,"autoTerminatedRelationships":["output stream","original","nonzero status"],"scheduledState":"ENABLED","retryCount":1,"retriedRelationships":["nonzero status"],"backoffMechanism":"PENALIZE_FLOWFILE","maxBackoffPeriod":"10 mins","componentType":"PROCESSOR","groupIdentifier":"815cd357-11aa-3cfb-aaac-b1dd73c18e5d"}],"inputPorts":[],"outputPorts":[],"connections":[{"identifier":"54ddc979-cb4c-3803-940b-0e049356ff41","instanceIdentifier":"da86d686-0193-1000-ffff-ffff8b65b5ec","name":"","source":{"id":"ade1b1fa-735c-3bcd-9e2c-bcd669a08fd5","type":"PROCESSOR","groupId":"815cd357-11aa-3cfb-aaac-b1dd73c18e5d","name":"GenerateFlowFile","comments":"","instanceIdentifier":"f4c935a4-b333-179a-b062-b2750579df49"},"destination":{"id":"ff4b6344-1914-3983-b83b-638ecf3f6a5b","type":"PROCESSOR","groupId":"815cd357-11aa-3cfb-aaac-b1dd73c18e5d","name":"ExecuteStreamCommand","comments":"","instanceIdentifier":"04813103-e9ec-1096-a010-ff5d5f10a3e5"},"labelIndex":1,"zIndex":0,"selectedRelationships":["success"],"backPressureObjectThreshold":10000,"backPressureDataSizeThreshold":"1 GB","flowFileExpiration":"0 sec","prioritizers":[],"bends":[],"loadBalanceStrategy":"DO_NOT_LOAD_BALANCE","partitioningAttribute":"","loadBalanceCompression":"DO_NOT_COMPRESS","componentType":"CONNECTION","groupIdentifier":"815cd357-11aa-3cfb-aaac-b1dd73c18e5d"},{"identifier":"5b8dd843-0685-3845-87f0-33848bf48997","instanceIdentifier":"daa13b77-0193-1000-ffff-ffffe6e1c20a","name":"","source":{"id":"bcc9cf26-45f5-31b6-8581-483021563543","type":"PROCESSOR","groupId":"815cd357-11aa-3cfb-aaac-b1dd73c18e5d","name":"GenerateFlowFile","comments":"","instanceIdentifier":"340d3f11-9acf-1275-a253-e3e74d6722e8"},"destination":{"id":"9b982326-c6fa-31ff-81f4-5a4c320d1423","type":"PROCESSOR","groupId":"815cd357-11aa-3cfb-aaac-b1dd73c18e5d","name":"ExecuteStreamCommand","comments":"","instanceIdentifier":"f1de315f-6cd4-1df8-b924-d164223f401b"},"labelIndex":1,"zIndex":0,"selectedRelationships":["success"],"backPressureObjectThreshold":10000,"backPressureDataSizeThreshold":"1 GB","flowFileExpiration":"0 sec","prioritizers":[],"bends":[],"loadBalanceStrategy":"DO_NOT_LOAD_BALANCE","partitioningAttribute":"","loadBalanceCompression":"DO_NOT_COMPRESS","componentType":"CONNECTION","groupIdentifier":"815cd357-11aa-3cfb-aaac-b1dd73c18e5d"},{"identifier":"e5ad798a-6136-30c3-bce3-8e7918511ba8","instanceIdentifier":"daa717ec-0193-1000-ffff-ffffbfc62f07","name":"","source":{"id":"9e1fc974-7d07-3f2f-aeec-fbade8950c0f","type":"PROCESSOR","groupId":"815cd357-11aa-3cfb-aaac-b1dd73c18e5d","name":"GenerateFlowFile","comments":"","instanceIdentifier":"a3e131fd-121a-14ab-b802-c5ac06e5cc30"},"destination":{"id":"2b68ebe8-b050-3af5-a68d-c01b6ca83efa","type":"PROCESSOR","groupId":"815cd357-11aa-3cfb-aaac-b1dd73c18e5d","name":"ExecuteStreamCommand","comments":"","instanceIdentifier":"1d8d3f74-ac39-15ac-90db-503ca4a7a46f"},"labelIndex":1,"zIndex":0,"selectedRelationships":["success"],"backPressureObjectThreshold":10000,"backPressureDataSizeThreshold":"1 GB","flowFileExpiration":"0 sec","prioritizers":[],"bends":[],"loadBalanceStrategy":"DO_NOT_LOAD_BALANCE","partitioningAttribute":"","loadBalanceCompression":"DO_NOT_COMPRESS","componentType":"CONNECTION","groupIdentifier":"815cd357-11aa-3cfb-aaac-b1dd73c18e5d"},{"identifier":"0306b8a8-e7fb-38f9-a0cd-c82117ddd919","instanceIdentifier":"d5ec2bd5-0193-1000-0000-0000170b1213","name":"","source":{"id":"81eb242a-10b5-3b5c-a035-01e2546e00db","type":"PROCESSOR","groupId":"815cd357-11aa-3cfb-aaac-b1dd73c18e5d","name":"GenerateFlowFile","comments":"","instanceIdentifier":"d5ebeb21-0193-1000-ffff-ffffc2e64bfc"},"destination":{"id":"2c32f191-13a2-36d0-817a-8f9b40bd4329","type":"PROCESSOR","groupId":"815cd357-11aa-3cfb-aaac-b1dd73c18e5d","name":"ExecuteStreamCommand","comments":"","instanceIdentifier":"d5ec1213-0193-1000-ffff-ffffcaf5eef1"},"labelIndex":1,"zIndex":0,"selectedRelationships":["success"],"backPressureObjectThreshold":10000,"backPressureDataSizeThreshold":"1 GB","flowFileExpiration":"0 sec","prioritizers":[],"bends":[],"loadBalanceStrategy":"DO_NOT_LOAD_BALANCE","partitioningAttribute":"","loadBalanceCompression":"DO_NOT_COMPRESS","componentType":"CONNECTION","groupIdentifier":"815cd357-11aa-3cfb-aaac-b1dd73c18e5d"}],"labels":[{"identifier":"51a567f8-5b32-3518-906f-f014fd8fd58d","instanceIdentifier":"c06f32d5-d6b2-1bbe-9be8-9b447465dd29","position":{"x":-152.0,"y":672.0},"label":"DAILY: Start Environments at 7am EST","zIndex":0,"width":520.0,"height":464.0,"style":{"background-color":"#0f7a1d","font-size":"16px"},"componentType":"LABEL","groupIdentifier":"815cd357-11aa-3cfb-aaac-b1dd73c18e5d"},{"identifier":"3538dea3-0a08-3f39-b5fc-700b198c26dd","instanceIdentifier":"da855692-0193-1000-ffff-ffff9ef1794c","position":{"x":456.0,"y":168.0},"label":"NIGHTLY: Stop Datahubs at 7pm EST","zIndex":0,"width":520.0,"height":464.0,"style":{"background-color":"#990000","font-size":"16px"},"componentType":"LABEL","groupIdentifier":"815cd357-11aa-3cfb-aaac-b1dd73c18e5d"},{"identifier":"8539542e-b2f1-30f4-9735-2ca66afb1e2c","instanceIdentifier":"ee363235-4636-1373-9ceb-e29afb058b99","position":{"x":456.0,"y":672.0},"label":"NIGHTLY: Stop Environment at 8pm EST","zIndex":0,"width":520.0,"height":464.0,"style":{"background-color":"#990000","font-size":"16px"},"componentType":"LABEL","groupIdentifier":"815cd357-11aa-3cfb-aaac-b1dd73c18e5d"},{"identifier":"085008a9-bc6d-30fe-8aa7-0f02d7fba046","instanceIdentifier":"ab743be4-b19b-1448-af09-afb09349e89d","position":{"x":-152.0,"y":168.0},"label":"DAILY: Start Datahubs at 8am EST","zIndex":0,"width":520.0,"height":464.0,"style":{"background-color":"#0f7a1d","font-size":"16px"},"componentType":"LABEL","groupIdentifier":"815cd357-11aa-3cfb-aaac-b1dd73c18e5d"}],"funnels":[],"controllerServices":[],"variables":{},"defaultFlowFileExpiration":"0 sec","defaultBackPressureObjectThreshold":10000,"defaultBackPressureDataSizeThreshold":"1 GB","flowFileConcurrency":"UNBOUNDED","flowFileOutboundPolicy":"STREAM_WHEN_AVAILABLE","componentType":"PROCESS_GROUP"},"externalControllerServices":{},"parameterContexts":{},"flowEncodingVersion":"1.0","parameterProviders":{},"latest":false}